claude_cortex-2.5.0.data/data/share/claude-cortex/docs/AI_INTELLIGENCE.md
claude_cortex-2.5.0.data/data/share/claude-cortex/docs/CHANGELOG.md
claude_cortex-2.5.0.data/data/share/claude-cortex/docs/CREDITS.md
claude_cortex-2.5.0.data/data/share/claude-cortex/docs/DIAGRAMS_README.md
claude_cortex-2.5.0.data/data/share/claude-cortex/docs/LICENSE
claude_cortex-2.5.0.data/data/share/claude-cortex/docs/README.md
claude_cortex-2.5.0.data/data/share/claude-cortex/docs/WHATS_NEW.md
claude_cortex-2.5.0.data/data/share/claude-cortex/docs/architecture-diagrams.md
claude_cortex-2.5.0.data/data/share/claude-cortex/docs/quick-reference.md
claude_cortex-2.5.0.data/data/share/man/man1/cortex-tui.1
claude_cortex-2.5.0.data/data/share/man/man1/cortex-workflow.1
claude_cortex-2.5.0.data/data/share/man/man1/cortex.1
claude_cortex-2.5.0.dist-info/licenses/LICENSE
claude_ctx_py/__init__.py
claude_ctx_py/activator.py
claude_ctx_py/analytics.py
claude_ctx_py/cli.py
claude_ctx_py/cmd_ai.py
claude_ctx_py/cmd_docs.py
claude_ctx_py/community.py
claude_ctx_py/completions.py
claude_ctx_py/composer.py
claude_ctx_py/error_utils.py
claude_ctx_py/exceptions.py
claude_ctx_py/init_cmds.py
claude_ctx_py/installer.py
claude_ctx_py/launcher.py
claude_ctx_py/messages.py
claude_ctx_py/metrics.py
claude_ctx_py/py.typed
claude_ctx_py/shell_integration.py
claude_ctx_py/skill_rating.py
claude_ctx_py/skill_rating_prompts.py
claude_ctx_py/skill_recommender.py
claude_ctx_py/slash_commands.py
claude_ctx_py/statusline.py
claude_ctx_py/suggester.py
claude_ctx_py/token_counter.py
claude_ctx_py/tui_command_palette.py
claude_ctx_py/tui_commands.py
claude_ctx_py/tui_dashboard.py
claude_ctx_py/tui_dialogs.py
claude_ctx_py/tui_extensions.py
claude_ctx_py/tui_format.py
claude_ctx_py/tui_graphs.py
claude_ctx_py/tui_icons.py
claude_ctx_py/tui_log_viewer.py
claude_ctx_py/tui_mcp.py
claude_ctx_py/tui_memory.py
claude_ctx_py/tui_navigation_providers.py
claude_ctx_py/tui_notifications.py
claude_ctx_py/tui_overview_enhanced.py
claude_ctx_py/tui_performance.py
claude_cortex-2.5.0.dist-info/METADATA
claude_cortex-2.5.0.dist-info/WHEEL
claude_cortex-2.5.0.dist-info/entry_points.txt
claude_cortex-2.5.0.dist-info/top_level.txt
claude_cortex-2.5.0.dist-info/RECORD
