Metadata-Version: 2.4
Name: claude-cortex
Version: 2.5.0
Summary: Python CLI/TUI and intelligent framework for managing Claude and other AI agents
Author-email: Nicholas Ferguson <ncf423@gmail.com>
License-Expression: MIT
Project-URL: Homepage, https://github.com/NickCrew/claude-cortex
Requires-Python: >=3.9
License-File: LICENSE
Requires-Dist: argcomplete>=3.2
Requires-Dist: rich>=13.0.0
Requires-Dist: textual>=0.47.0
Requires-Dist: PyYAML>=6.0.0
Requires-Dist: psutil>=5.9.0
Requires-Dist: jsonplate>=0.0.1
Requires-Dist: jsonschema>=4.25.1
Provides-Extra: ai
Requires-Dist: fastembed>=0.7.4; extra == "ai"
Requires-Dist: numpy>=1.24.0; extra == "ai"
Provides-Extra: llm
Requires-Dist: anthropic>=0.18.0; extra == "llm"
Provides-Extra: dev
Requires-Dist: pytest>=7.4.0; extra == "dev"
Requires-Dist: pytest-cov>=4.1.0; extra == "dev"
Requires-Dist: pytest-mock>=3.12.0; extra == "dev"
Requires-Dist: mypy>=1.7.0; extra == "dev"
Requires-Dist: types-PyYAML>=6.0.0; extra == "dev"
Requires-Dist: types-psutil>=5.9.0; extra == "dev"
Requires-Dist: black>=23.0.0; extra == "dev"
Requires-Dist: PyYAML>=6.0.0; extra == "dev"
Requires-Dist: build>=1.0.0; extra == "dev"
Requires-Dist: python-semantic-release>=9.0.0; extra == "dev"
Provides-Extra: all
Requires-Dist: fastembed>=0.7.4; extra == "all"
Requires-Dist: numpy>=1.24.0; extra == "all"
Requires-Dist: anthropic>=0.18.0; extra == "all"
Dynamic: license-file
